prelude_sdk/__init__.py
prelude_sdk/controllers/__init__.py
prelude_sdk/controllers/build_controller.py
prelude_sdk/controllers/detect_controller.py
prelude_sdk/controllers/export_controller.py
prelude_sdk/controllers/generate_controller.py
prelude_sdk/controllers/http_controller.py
prelude_sdk/controllers/iam_controller.py
prelude_sdk/controllers/jobs_controller.py
prelude_sdk/controllers/partner_controller.py
prelude_sdk/controllers/probe_controller.py
prelude_sdk/controllers/scm_controller.py
prelude_sdk/models/__init__.py
prelude_sdk/models/account.py
prelude_sdk/models/codes.py
prelude_sdk-2.6.42.dist-info/licenses/LICENSE
prelude_sdk-2.6.42.dist-info/METADATA
prelude_sdk-2.6.42.dist-info/WHEEL
prelude_sdk-2.6.42.dist-info/top_level.txt
prelude_sdk-2.6.42.dist-info/RECORD
