Metadata-Version: 2.4
Name: prelude-sdk
Version: 2.6.42
Summary: For interacting with the Prelude API
Home-page: https://github.com/preludeorg
Author: Prelude Research
Author-email: support@preludesecurity.com
Classifier: Programming Language :: Python :: 3
Classifier: License :: OSI Approved :: MIT License
Classifier: Operating System :: OS Independent
Requires-Python: >=3.10
License-File: LICENSE
Requires-Dist: requests
Dynamic: license-file
